elephant_socks5/__init__.py
elephant_socks5/protocol.py
elephant_socks5/utils.py
elephant_socks5/version.py
test/__init__.py
test/test_init.py
test/test_protocol.py
test/test_utils.py
elephant_socks5-0.0.30.dist-info/LICENSE
elephant_socks5-0.0.30.dist-info/METADATA
elephant_socks5-0.0.30.dist-info/WHEEL
elephant_socks5-0.0.30.dist-info/entry_points.txt
elephant_socks5-0.0.30.dist-info/top_level.txt
elephant_socks5-0.0.30.dist-info/RECORD
